{"nodes": [{"id": "requirements_pyqt6_webengine", "label": "PyQt6-WebEngine>=6.6.0", "file_type": "code", "source_file": "requirements.txt", "source_location": null}, {"id": "requirements_pyqt6", "label": "PyQt6>=6.6.0", "file_type": "code", "source_file": "requirements.txt", "source_location": null}, {"id": "requirements_python_docx", "label": "python-docx>=1.1", "file_type": "code", "source_file": "requirements.txt", "source_location": null}], "edges": [{"source": "requirements_pyqt6_webengine", "target": "requirements_pyqt6", "relation": "references", "confidence": "EXTRACTED", "confidence_score": 1.0, "source_file": "requirements.txt"}], "hyperedges": []}