{"nodes": [{"id": "c_users_marci_documents_github_permadesign_tests_test_fauna_py", "label": "test_fauna.py", "file_type": "code", "source_file": "C:\\Users\\Marci\\Documents\\GitHub\\PermaDesign\\tests\\test_fauna.py", "source_location": "L1"}, {"id": "tests_test_fauna_pid", "label": "_pid()", "file_type": "code", "source_file": "C:\\Users\\Marci\\Documents\\GitHub\\PermaDesign\\tests\\test_fauna.py", "source_location": "L38"}, {"id": "str", "label": "str", "file_type": "code", "source_file": "C:\\Users\\Marci\\Documents\\GitHub\\PermaDesign\\tests\\test_fauna.py", "source_location": "L38"}, {"id": "int", "label": "int", "file_type": "code", "source_file": "C:\\Users\\Marci\\Documents\\GitHub\\PermaDesign\\tests\\test_fauna.py", "source_location": "L38"}, {"id": "tests_test_fauna_fid", "label": "_fid()", "file_type": "code", "source_file": "C:\\Users\\Marci\\Documents\\GitHub\\PermaDesign\\tests\\test_fauna.py", "source_location": "L49"}, {"id": "tests_test_fauna_testfaunaschema", "label": "TestFaunaSchema", "file_type": "code", "source_file": "C:\\Users\\Marci\\Documents\\GitHub\\PermaDesign\\tests\\test_fauna.py", "source_location": "L60"}, {"id": "tests_test_fauna_setupclass", "label": "setUpClass()", "file_type": "code", "source_file": "C:\\Users\\Marci\\Documents\\GitHub\\PermaDesign\\tests\\test_fauna.py", "source_location": "L63"}, {"id": "tests_test_fauna_testfaunaschema_test_fauna_table_populated", "label": ".test_fauna_table_populated()", "file_type": "code", "source_file": "C:\\Users\\Marci\\Documents\\GitHub\\PermaDesign\\tests\\test_fauna.py", "source_location": "L68"}, {"id": "tests_test_fauna_testfaunaschema_test_lepidoptera_present", "label": ".test_lepidoptera_present()", "file_type": "code", "source_file": "C:\\Users\\Marci\\Documents\\GitHub\\PermaDesign\\tests\\test_fauna.py", "source_location": "L73"}, {"id": "tests_test_fauna_testfaunaschema_test_birds_present", "label": ".test_birds_present()", "file_type": "code", "source_file": "C:\\Users\\Marci\\Documents\\GitHub\\PermaDesign\\tests\\test_fauna.py", "source_location": "L78"}, {"id": "tests_test_fauna_testfaunaschema_test_bees_present", "label": ".test_bees_present()", "file_type": "code", "source_file": "C:\\Users\\Marci\\Documents\\GitHub\\PermaDesign\\tests\\test_fauna.py", "source_location": "L82"}, {"id": "tests_test_fauna_testfaunaschema_test_monarch_only_hosts_on_milkweed", "label": ".test_monarch_only_hosts_on_milkweed()", "file_type": "code", "source_file": "C:\\Users\\Marci\\Documents\\GitHub\\PermaDesign\\tests\\test_fauna.py", "source_location": "L88"}, {"id": "tests_test_fauna_testfaunaschema_test_showy_milkweed_links_to_monarch_as_specialist", "label": ".test_showy_milkweed_links_to_monarch_as_specialist()", "file_type": "code", "source_file": "C:\\Users\\Marci\\Documents\\GitHub\\PermaDesign\\tests\\test_fauna.py", "source_location": "L104"}, {"id": "tests_test_fauna_testfaunaschema_test_aspen_is_lepidoptera_keystone", "label": ".test_aspen_is_lepidoptera_keystone()", "file_type": "code", "source_file": "C:\\Users\\Marci\\Documents\\GitHub\\PermaDesign\\tests\\test_fauna.py", "source_location": "L116"}, {"id": "tests_test_fauna_testfaunaschema_test_pussy_willow_supports_yellow_warbler_nesting", "label": ".test_pussy_willow_supports_yellow_warbler_nesting()", "file_type": "code", "source_file": "C:\\Users\\Marci\\Documents\\GitHub\\PermaDesign\\tests\\test_fauna.py", "source_location": "L124"}, {"id": "tests_test_fauna_testfaunaschema_test_lepidoptera_supported_by_single_milkweed_includes_monarch", "label": ".test_lepidoptera_supported_by_single_milkweed_includes_monarch()", "file_type": "code", "source_file": "C:\\Users\\Marci\\Documents\\GitHub\\PermaDesign\\tests\\test_fauna.py", "source_location": "L135"}, {"id": "tests_test_fauna_testfaunaschema_test_lepidoptera_supported_empty_input", "label": ".test_lepidoptera_supported_empty_input()", "file_type": "code", "source_file": "C:\\Users\\Marci\\Documents\\GitHub\\PermaDesign\\tests\\test_fauna.py", "source_location": "L141"}, {"id": "tests_test_fauna_testfaunaschema_test_lepidoptera_supported_union_grows_with_more_plants", "label": ".test_lepidoptera_supported_union_grows_with_more_plants()", "file_type": "code", "source_file": "C:\\Users\\Marci\\Documents\\GitHub\\PermaDesign\\tests\\test_fauna.py", "source_location": "L144"}, {"id": "tests_test_fauna_testfaunaschema_test_fauna_supported_per_taxon", "label": ".test_fauna_supported_per_taxon()", "file_type": "code", "source_file": "C:\\Users\\Marci\\Documents\\GitHub\\PermaDesign\\tests\\test_fauna.py", "source_location": "L157"}, {"id": "tests_test_fauna_rationale_1", "label": "tests/test_fauna.py  Verifies the schema v13 / V1.31 ``fauna`` registry and ``", "file_type": "rationale", "source_file": "C:\\Users\\Marci\\Documents\\GitHub\\PermaDesign\\tests\\test_fauna.py", "source_location": "L1"}], "edges": [{"source": "c_users_marci_documents_github_permadesign_tests_test_fauna_py", "target": "os", "relation": "imports", "context": "import", "confidence": "EXTRACTED", "source_file": "C:\\Users\\Marci\\Documents\\GitHub\\PermaDesign\\tests\\test_fauna.py", "source_location": "L12", "weight": 1.0}, {"source": "c_users_marci_documents_github_permadesign_tests_test_fauna_py", "target": "sys", "relation": "imports", "context": "import", "confidence": "EXTRACTED", "source_file": "C:\\Users\\Marci\\Documents\\GitHub\\PermaDesign\\tests\\test_fauna.py", "source_location": "L13", "weight": 1.0}, {"source": "c_users_marci_documents_github_permadesign_tests_test_fauna_py", "target": "tempfile", "relation": "imports", "context": "import", "confidence": "EXTRACTED", "source_file": "C:\\Users\\Marci\\Documents\\GitHub\\PermaDesign\\tests\\test_fauna.py", "source_location": "L14", "weight": 1.0}, {"source": "c_users_marci_documents_github_permadesign_tests_test_fauna_py", "target": "unittest", "relation": "imports", "context": "import", "confidence": "EXTRACTED", "source_file": "C:\\Users\\Marci\\Documents\\GitHub\\PermaDesign\\tests\\test_fauna.py", "source_location": "L15", "weight": 1.0}, {"source": "c_users_marci_documents_github_permadesign_tests_test_fauna_py", "target": "src_db_plants", "relation": "imports", "context": "import", "confidence": "EXTRACTED", "source_file": "C:\\Users\\Marci\\Documents\\GitHub\\PermaDesign\\tests\\test_fauna.py", "source_location": "L22", "weight": 1.0}, {"source": "c_users_marci_documents_github_permadesign_tests_test_fauna_py", "target": "src_db_plants", "relation": "imports_from", "context": "import", "confidence": "EXTRACTED", "source_file": "C:\\Users\\Marci\\Documents\\GitHub\\PermaDesign\\tests\\test_fauna.py", "source_location": "L27", "weight": 1.0}, {"source": "c_users_marci_documents_github_permadesign_tests_test_fauna_py", "target": "src_db_fauna", "relation": "imports_from", "context": "import", "confidence": "EXTRACTED", "source_file": "C:\\Users\\Marci\\Documents\\GitHub\\PermaDesign\\tests\\test_fauna.py", "source_location": "L28", "weight": 1.0}, {"source": "c_users_marci_documents_github_permadesign_tests_test_fauna_py", "target": "tests_test_fauna_pid", "relation": "contains", "confidence": "EXTRACTED", "source_file": "C:\\Users\\Marci\\Documents\\GitHub\\PermaDesign\\tests\\test_fauna.py", "source_location": "L38", "weight": 1.0}, {"source": "tests_test_fauna_pid", "target": "str", "relation": "references", "context": "parameter_type", "confidence": "EXTRACTED", "source_file": "C:\\Users\\Marci\\Documents\\GitHub\\PermaDesign\\tests\\test_fauna.py", "source_location": "L38", "weight": 1.0}, {"source": "tests_test_fauna_pid", "target": "int", "relation": "references", "context": "return_type", "confidence": "EXTRACTED", "source_file": "C:\\Users\\Marci\\Documents\\GitHub\\PermaDesign\\tests\\test_fauna.py", "source_location": "L38", "weight": 1.0}, {"source": "c_users_marci_documents_github_permadesign_tests_test_fauna_py", "target": "tests_test_fauna_fid", "relation": "contains", "confidence": "EXTRACTED", "source_file": "C:\\Users\\Marci\\Documents\\GitHub\\PermaDesign\\tests\\test_fauna.py", "source_location": "L49", "weight": 1.0}, {"source": "tests_test_fauna_fid", "target": "str", "relation": "references", "context": "parameter_type", "confidence": "EXTRACTED", "source_file": "C:\\Users\\Marci\\Documents\\GitHub\\PermaDesign\\tests\\test_fauna.py", "source_location": "L49", "weight": 1.0}, {"source": "tests_test_fauna_fid", "target": "int", "relation": "references", "context": "return_type", "confidence": "EXTRACTED", "source_file": "C:\\Users\\Marci\\Documents\\GitHub\\PermaDesign\\tests\\test_fauna.py", "source_location": "L49", "weight": 1.0}, {"source": "c_users_marci_documents_github_permadesign_tests_test_fauna_py", "target": "tests_test_fauna_testfaunaschema", "relation": "contains", "confidence": "EXTRACTED", "source_file": "C:\\Users\\Marci\\Documents\\GitHub\\PermaDesign\\tests\\test_fauna.py", "source_location": "L60", "weight": 1.0}, {"source": "c_users_marci_documents_github_permadesign_tests_test_fauna_py", "target": "tests_test_fauna_setupclass", "relation": "contains", "confidence": "EXTRACTED", "source_file": "C:\\Users\\Marci\\Documents\\GitHub\\PermaDesign\\tests\\test_fauna.py", "source_location": "L63", "weight": 1.0}, {"source": "tests_test_fauna_testfaunaschema", "target": "tests_test_fauna_testfaunaschema_test_fauna_table_populated", "relation": "method", "confidence": "EXTRACTED", "source_file": "C:\\Users\\Marci\\Documents\\GitHub\\PermaDesign\\tests\\test_fauna.py", "source_location": "L68", "weight": 1.0}, {"source": "tests_test_fauna_testfaunaschema", "target": "tests_test_fauna_testfaunaschema_test_lepidoptera_present", "relation": "method", "confidence": "EXTRACTED", "source_file": "C:\\Users\\Marci\\Documents\\GitHub\\PermaDesign\\tests\\test_fauna.py", "source_location": "L73", "weight": 1.0}, {"source": "tests_test_fauna_testfaunaschema", "target": "tests_test_fauna_testfaunaschema_test_birds_present", "relation": "method", "confidence": "EXTRACTED", "source_file": "C:\\Users\\Marci\\Documents\\GitHub\\PermaDesign\\tests\\test_fauna.py", "source_location": "L78", "weight": 1.0}, {"source": "tests_test_fauna_testfaunaschema", "target": "tests_test_fauna_testfaunaschema_test_bees_present", "relation": "method", "confidence": "EXTRACTED", "source_file": "C:\\Users\\Marci\\Documents\\GitHub\\PermaDesign\\tests\\test_fauna.py", "source_location": "L82", "weight": 1.0}, {"source": "tests_test_fauna_testfaunaschema", "target": "tests_test_fauna_testfaunaschema_test_monarch_only_hosts_on_milkweed", "relation": "method", "confidence": "EXTRACTED", "source_file": "C:\\Users\\Marci\\Documents\\GitHub\\PermaDesign\\tests\\test_fauna.py", "source_location": "L88", "weight": 1.0}, {"source": "tests_test_fauna_testfaunaschema", "target": "tests_test_fauna_testfaunaschema_test_showy_milkweed_links_to_monarch_as_specialist", "relation": "method", "confidence": "EXTRACTED", "source_file": "C:\\Users\\Marci\\Documents\\GitHub\\PermaDesign\\tests\\test_fauna.py", "source_location": "L104", "weight": 1.0}, {"source": "tests_test_fauna_testfaunaschema", "target": "tests_test_fauna_testfaunaschema_test_aspen_is_lepidoptera_keystone", "relation": "method", "confidence": "EXTRACTED", "source_file": "C:\\Users\\Marci\\Documents\\GitHub\\PermaDesign\\tests\\test_fauna.py", "source_location": "L116", "weight": 1.0}, {"source": "tests_test_fauna_testfaunaschema", "target": "tests_test_fauna_testfaunaschema_test_pussy_willow_supports_yellow_warbler_nesting", "relation": "method", "confidence": "EXTRACTED", "source_file": "C:\\Users\\Marci\\Documents\\GitHub\\PermaDesign\\tests\\test_fauna.py", "source_location": "L124", "weight": 1.0}, {"source": "tests_test_fauna_testfaunaschema", "target": "tests_test_fauna_testfaunaschema_test_lepidoptera_supported_by_single_milkweed_includes_monarch", "relation": "method", "confidence": "EXTRACTED", "source_file": "C:\\Users\\Marci\\Documents\\GitHub\\PermaDesign\\tests\\test_fauna.py", "source_location": "L135", "weight": 1.0}, {"source": "tests_test_fauna_testfaunaschema", "target": "tests_test_fauna_testfaunaschema_test_lepidoptera_supported_empty_input", "relation": "method", "confidence": "EXTRACTED", "source_file": "C:\\Users\\Marci\\Documents\\GitHub\\PermaDesign\\tests\\test_fauna.py", "source_location": "L141", "weight": 1.0}, {"source": "tests_test_fauna_testfaunaschema", "target": "tests_test_fauna_testfaunaschema_test_lepidoptera_supported_union_grows_with_more_plants", "relation": "method", "confidence": "EXTRACTED", "source_file": "C:\\Users\\Marci\\Documents\\GitHub\\PermaDesign\\tests\\test_fauna.py", "source_location": "L144", "weight": 1.0}, {"source": "tests_test_fauna_testfaunaschema", "target": "tests_test_fauna_testfaunaschema_test_fauna_supported_per_taxon", "relation": "method", "confidence": "EXTRACTED", "source_file": "C:\\Users\\Marci\\Documents\\GitHub\\PermaDesign\\tests\\test_fauna.py", "source_location": "L157", "weight": 1.0}, {"source": "tests_test_fauna_testfaunaschema_test_monarch_only_hosts_on_milkweed", "target": "tests_test_fauna_fid", "relation": "calls", "context": "call", "confidence": "EXTRACTED", "source_file": "C:\\Users\\Marci\\Documents\\GitHub\\PermaDesign\\tests\\test_fauna.py", "source_location": "L89", "weight": 1.0}, {"source": "tests_test_fauna_testfaunaschema_test_showy_milkweed_links_to_monarch_as_specialist", "target": "tests_test_fauna_pid", "relation": "calls", "context": "call", "confidence": "EXTRACTED", "source_file": "C:\\Users\\Marci\\Documents\\GitHub\\PermaDesign\\tests\\test_fauna.py", "source_location": "L105", "weight": 1.0}, {"source": "tests_test_fauna_testfaunaschema_test_aspen_is_lepidoptera_keystone", "target": "tests_test_fauna_pid", "relation": "calls", "context": "call", "confidence": "EXTRACTED", "source_file": "C:\\Users\\Marci\\Documents\\GitHub\\PermaDesign\\tests\\test_fauna.py", "source_location": "L117", "weight": 1.0}, {"source": "tests_test_fauna_testfaunaschema_test_pussy_willow_supports_yellow_warbler_nesting", "target": "tests_test_fauna_pid", "relation": "calls", "context": "call", "confidence": "EXTRACTED", "source_file": "C:\\Users\\Marci\\Documents\\GitHub\\PermaDesign\\tests\\test_fauna.py", "source_location": "L125", "weight": 1.0}, {"source": "tests_test_fauna_testfaunaschema_test_lepidoptera_supported_by_single_milkweed_includes_monarch", "target": "tests_test_fauna_pid", "relation": "calls", "context": "call", "confidence": "EXTRACTED", "source_file": "C:\\Users\\Marci\\Documents\\GitHub\\PermaDesign\\tests\\test_fauna.py", "source_location": "L136", "weight": 1.0}, {"source": "tests_test_fauna_testfaunaschema_test_lepidoptera_supported_by_single_milkweed_includes_monarch", "target": "tests_test_fauna_fid", "relation": "calls", "context": "call", "confidence": "EXTRACTED", "source_file": "C:\\Users\\Marci\\Documents\\GitHub\\PermaDesign\\tests\\test_fauna.py", "source_location": "L138", "weight": 1.0}, {"source": "tests_test_fauna_testfaunaschema_test_lepidoptera_supported_union_grows_with_more_plants", "target": "tests_test_fauna_pid", "relation": "calls", "context": "call", "confidence": "EXTRACTED", "source_file": "C:\\Users\\Marci\\Documents\\GitHub\\PermaDesign\\tests\\test_fauna.py", "source_location": "L145", "weight": 1.0}, {"source": "tests_test_fauna_testfaunaschema_test_lepidoptera_supported_union_grows_with_more_plants", "target": "tests_test_fauna_fid", "relation": "calls", "context": "call", "confidence": "EXTRACTED", "source_file": "C:\\Users\\Marci\\Documents\\GitHub\\PermaDesign\\tests\\test_fauna.py", "source_location": "L155", "weight": 1.0}, {"source": "tests_test_fauna_testfaunaschema_test_fauna_supported_per_taxon", "target": "tests_test_fauna_pid", "relation": "calls", "context": "call", "confidence": "EXTRACTED", "source_file": "C:\\Users\\Marci\\Documents\\GitHub\\PermaDesign\\tests\\test_fauna.py", "source_location": "L158", "weight": 1.0}, {"source": "tests_test_fauna_rationale_1", "target": "c_users_marci_documents_github_permadesign_tests_test_fauna_py", "relation": "rationale_for", "confidence": "EXTRACTED", "source_file": "C:\\Users\\Marci\\Documents\\GitHub\\PermaDesign\\tests\\test_fauna.py", "source_location": "L1", "weight": 1.0}], "raw_calls": [{"caller_nid": "tests_test_fauna_pid", "callee": "get_connection", "is_member_call": false, "source_file": "C:\\Users\\Marci\\Documents\\GitHub\\PermaDesign\\tests\\test_fauna.py", "source_location": "L39"}, {"caller_nid": "tests_test_fauna_pid", "callee": "fetchone", "is_member_call": true, "source_file": "C:\\Users\\Marci\\Documents\\GitHub\\PermaDesign\\tests\\test_fauna.py", "source_location": "L41"}, {"caller_nid": "tests_test_fauna_pid", "callee": "execute", "is_member_call": true, "source_file": "C:\\Users\\Marci\\Documents\\GitHub\\PermaDesign\\tests\\test_fauna.py", "source_location": "L41"}, {"caller_nid": "tests_test_fauna_pid", "callee": "close", "is_member_call": true, "source_file": "C:\\Users\\Marci\\Documents\\GitHub\\PermaDesign\\tests\\test_fauna.py", "source_location": "L46"}, {"caller_nid": "tests_test_fauna_fid", "callee": "get_connection", "is_member_call": false, "source_file": "C:\\Users\\Marci\\Documents\\GitHub\\PermaDesign\\tests\\test_fauna.py", "source_location": "L50"}, {"caller_nid": "tests_test_fauna_fid", "callee": "fetchone", "is_member_call": true, "source_file": "C:\\Users\\Marci\\Documents\\GitHub\\PermaDesign\\tests\\test_fauna.py", "source_location": "L52"}, {"caller_nid": "tests_test_fauna_fid", "callee": "execute", "is_member_call": true, "source_file": "C:\\Users\\Marci\\Documents\\GitHub\\PermaDesign\\tests\\test_fauna.py", "source_location": "L52"}, {"caller_nid": "tests_test_fauna_fid", "callee": "close", "is_member_call": true, "source_file": "C:\\Users\\Marci\\Documents\\GitHub\\PermaDesign\\tests\\test_fauna.py", "source_location": "L57"}, {"caller_nid": "tests_test_fauna_setupclass", "callee": "init_db", "is_member_call": false, "source_file": "C:\\Users\\Marci\\Documents\\GitHub\\PermaDesign\\tests\\test_fauna.py", "source_location": "L64"}, {"caller_nid": "tests_test_fauna_testfaunaschema_test_fauna_table_populated", "callee": "list_fauna", "is_member_call": false, "source_file": "C:\\Users\\Marci\\Documents\\GitHub\\PermaDesign\\tests\\test_fauna.py", "source_location": "L69"}, {"caller_nid": "tests_test_fauna_testfaunaschema_test_fauna_table_populated", "callee": "assertGreater", "is_member_call": true, "source_file": "C:\\Users\\Marci\\Documents\\GitHub\\PermaDesign\\tests\\test_fauna.py", "source_location": "L70"}, {"caller_nid": "tests_test_fauna_testfaunaschema_test_fauna_table_populated", "callee": "len", "is_member_call": false, "source_file": "C:\\Users\\Marci\\Documents\\GitHub\\PermaDesign\\tests\\test_fauna.py", "source_location": "L70"}, {"caller_nid": "tests_test_fauna_testfaunaschema_test_lepidoptera_present", "callee": "list_fauna", "is_member_call": false, "source_file": "C:\\Users\\Marci\\Documents\\GitHub\\PermaDesign\\tests\\test_fauna.py", "source_location": "L74"}, {"caller_nid": "tests_test_fauna_testfaunaschema_test_lepidoptera_present", "callee": "assertGreater", "is_member_call": true, "source_file": "C:\\Users\\Marci\\Documents\\GitHub\\PermaDesign\\tests\\test_fauna.py", "source_location": "L75"}, {"caller_nid": "tests_test_fauna_testfaunaschema_test_lepidoptera_present", "callee": "len", "is_member_call": false, "source_file": "C:\\Users\\Marci\\Documents\\GitHub\\PermaDesign\\tests\\test_fauna.py", "source_location": "L75"}, {"caller_nid": "tests_test_fauna_testfaunaschema_test_birds_present", "callee": "list_fauna", "is_member_call": false, "source_file": "C:\\Users\\Marci\\Documents\\GitHub\\PermaDesign\\tests\\test_fauna.py", "source_location": "L79"}, {"caller_nid": "tests_test_fauna_testfaunaschema_test_birds_present", "callee": "assertGreater", "is_member_call": true, "source_file": "C:\\Users\\Marci\\Documents\\GitHub\\PermaDesign\\tests\\test_fauna.py", "source_location": "L80"}, {"caller_nid": "tests_test_fauna_testfaunaschema_test_birds_present", "callee": "len", "is_member_call": false, "source_file": "C:\\Users\\Marci\\Documents\\GitHub\\PermaDesign\\tests\\test_fauna.py", "source_location": "L80"}, {"caller_nid": "tests_test_fauna_testfaunaschema_test_bees_present", "callee": "list_fauna", "is_member_call": false, "source_file": "C:\\Users\\Marci\\Documents\\GitHub\\PermaDesign\\tests\\test_fauna.py", "source_location": "L83"}, {"caller_nid": "tests_test_fauna_testfaunaschema_test_bees_present", "callee": "assertGreater", "is_member_call": true, "source_file": "C:\\Users\\Marci\\Documents\\GitHub\\PermaDesign\\tests\\test_fauna.py", "source_location": "L84"}, {"caller_nid": "tests_test_fauna_testfaunaschema_test_bees_present", "callee": "len", "is_member_call": false, "source_file": "C:\\Users\\Marci\\Documents\\GitHub\\PermaDesign\\tests\\test_fauna.py", "source_location": "L84"}, {"caller_nid": "tests_test_fauna_testfaunaschema_test_monarch_only_hosts_on_milkweed", "callee": "assertIsNotNone", "is_member_call": true, "source_file": "C:\\Users\\Marci\\Documents\\GitHub\\PermaDesign\\tests\\test_fauna.py", "source_location": "L90"}, {"caller_nid": "tests_test_fauna_testfaunaschema_test_monarch_only_hosts_on_milkweed", "callee": "plants_for_fauna", "is_member_call": false, "source_file": "C:\\Users\\Marci\\Documents\\GitHub\\PermaDesign\\tests\\test_fauna.py", "source_location": "L91"}, {"caller_nid": "tests_test_fauna_testfaunaschema_test_monarch_only_hosts_on_milkweed", "callee": "assertIn", "is_member_call": true, "source_file": "C:\\Users\\Marci\\Documents\\GitHub\\PermaDesign\\tests\\test_fauna.py", "source_location": "L95"}, {"caller_nid": "tests_test_fauna_testfaunaschema_test_monarch_only_hosts_on_milkweed", "callee": "assertIn", "is_member_call": true, "source_file": "C:\\Users\\Marci\\Documents\\GitHub\\PermaDesign\\tests\\test_fauna.py", "source_location": "L96"}, {"caller_nid": "tests_test_fauna_testfaunaschema_test_monarch_only_hosts_on_milkweed", "callee": "lower", "is_member_call": true, "source_file": "C:\\Users\\Marci\\Documents\\GitHub\\PermaDesign\\tests\\test_fauna.py", "source_location": "L98"}, {"caller_nid": "tests_test_fauna_testfaunaschema_test_monarch_only_hosts_on_milkweed", "callee": "get", "is_member_call": true, "source_file": "C:\\Users\\Marci\\Documents\\GitHub\\PermaDesign\\tests\\test_fauna.py", "source_location": "L98"}, {"caller_nid": "tests_test_fauna_testfaunaschema_test_monarch_only_hosts_on_milkweed", "callee": "assertTrue", "is_member_call": true, "source_file": "C:\\Users\\Marci\\Documents\\GitHub\\PermaDesign\\tests\\test_fauna.py", "source_location": "L99"}, {"caller_nid": "tests_test_fauna_testfaunaschema_test_monarch_only_hosts_on_milkweed", "callee": "startswith", "is_member_call": true, "source_file": "C:\\Users\\Marci\\Documents\\GitHub\\PermaDesign\\tests\\test_fauna.py", "source_location": "L100"}, {"caller_nid": "tests_test_fauna_testfaunaschema_test_showy_milkweed_links_to_monarch_as_specialist", "callee": "assertIsNotNone", "is_member_call": true, "source_file": "C:\\Users\\Marci\\Documents\\GitHub\\PermaDesign\\tests\\test_fauna.py", "source_location": "L106"}, {"caller_nid": "tests_test_fauna_testfaunaschema_test_showy_milkweed_links_to_monarch_as_specialist", "callee": "fauna_for_plant", "is_member_call": false, "source_file": "C:\\Users\\Marci\\Documents\\GitHub\\PermaDesign\\tests\\test_fauna.py", "source_location": "L107"}, {"caller_nid": "tests_test_fauna_testfaunaschema_test_showy_milkweed_links_to_monarch_as_specialist", "callee": "get", "is_member_call": true, "source_file": "C:\\Users\\Marci\\Documents\\GitHub\\PermaDesign\\tests\\test_fauna.py", "source_location": "L110"}, {"caller_nid": "tests_test_fauna_testfaunaschema_test_showy_milkweed_links_to_monarch_as_specialist", "callee": "get", "is_member_call": true, "source_file": "C:\\Users\\Marci\\Documents\\GitHub\\PermaDesign\\tests\\test_fauna.py", "source_location": "L111"}, {"caller_nid": "tests_test_fauna_testfaunaschema_test_showy_milkweed_links_to_monarch_as_specialist", "callee": "assertEqual", "is_member_call": true, "source_file": "C:\\Users\\Marci\\Documents\\GitHub\\PermaDesign\\tests\\test_fauna.py", "source_location": "L113"}, {"caller_nid": "tests_test_fauna_testfaunaschema_test_showy_milkweed_links_to_monarch_as_specialist", "callee": "len", "is_member_call": false, "source_file": "C:\\Users\\Marci\\Documents\\GitHub\\PermaDesign\\tests\\test_fauna.py", "source_location": "L113"}, {"caller_nid": "tests_test_fauna_testfaunaschema_test_showy_milkweed_links_to_monarch_as_specialist", "callee": "assertEqual", "is_member_call": true, "source_file": "C:\\Users\\Marci\\Documents\\GitHub\\PermaDesign\\tests\\test_fauna.py", "source_location": "L114"}, {"caller_nid": "tests_test_fauna_testfaunaschema_test_aspen_is_lepidoptera_keystone", "callee": "assertIsNotNone", "is_member_call": true, "source_file": "C:\\Users\\Marci\\Documents\\GitHub\\PermaDesign\\tests\\test_fauna.py", "source_location": "L118"}, {"caller_nid": "tests_test_fauna_testfaunaschema_test_aspen_is_lepidoptera_keystone", "callee": "keystone_rank_lepidoptera", "is_member_call": false, "source_file": "C:\\Users\\Marci\\Documents\\GitHub\\PermaDesign\\tests\\test_fauna.py", "source_location": "L121"}, {"caller_nid": "tests_test_fauna_testfaunaschema_test_aspen_is_lepidoptera_keystone", "callee": "assertGreaterEqual", "is_member_call": true, "source_file": "C:\\Users\\Marci\\Documents\\GitHub\\PermaDesign\\tests\\test_fauna.py", "source_location": "L122"}, {"caller_nid": "tests_test_fauna_testfaunaschema_test_pussy_willow_supports_yellow_warbler_nesting", "callee": "assertIsNotNone", "is_member_call": true, "source_file": "C:\\Users\\Marci\\Documents\\GitHub\\PermaDesign\\tests\\test_fauna.py", "source_location": "L126"}, {"caller_nid": "tests_test_fauna_testfaunaschema_test_pussy_willow_supports_yellow_warbler_nesting", "callee": "fauna_for_plant", "is_member_call": false, "source_file": "C:\\Users\\Marci\\Documents\\GitHub\\PermaDesign\\tests\\test_fauna.py", "source_location": "L127"}, {"caller_nid": "tests_test_fauna_testfaunaschema_test_pussy_willow_supports_yellow_warbler_nesting", "callee": "get", "is_member_call": true, "source_file": "C:\\Users\\Marci\\Documents\\GitHub\\PermaDesign\\tests\\test_fauna.py", "source_location": "L129"}, {"caller_nid": "tests_test_fauna_testfaunaschema_test_pussy_willow_supports_yellow_warbler_nesting", "callee": "get", "is_member_call": true, "source_file": "C:\\Users\\Marci\\Documents\\GitHub\\PermaDesign\\tests\\test_fauna.py", "source_location": "L130"}, {"caller_nid": "tests_test_fauna_testfaunaschema_test_pussy_willow_supports_yellow_warbler_nesting", "callee": "assertEqual", "is_member_call": true, "source_file": "C:\\Users\\Marci\\Documents\\GitHub\\PermaDesign\\tests\\test_fauna.py", "source_location": "L131"}, {"caller_nid": "tests_test_fauna_testfaunaschema_test_pussy_willow_supports_yellow_warbler_nesting", "callee": "len", "is_member_call": false, "source_file": "C:\\Users\\Marci\\Documents\\GitHub\\PermaDesign\\tests\\test_fauna.py", "source_location": "L131"}, {"caller_nid": "tests_test_fauna_testfaunaschema_test_lepidoptera_supported_by_single_milkweed_includes_monarch", "callee": "lepidoptera_supported_by_plants", "is_member_call": false, "source_file": "C:\\Users\\Marci\\Documents\\GitHub\\PermaDesign\\tests\\test_fauna.py", "source_location": "L137"}, {"caller_nid": "tests_test_fauna_testfaunaschema_test_lepidoptera_supported_by_single_milkweed_includes_monarch", "callee": "assertIn", "is_member_call": true, "source_file": "C:\\Users\\Marci\\Documents\\GitHub\\PermaDesign\\tests\\test_fauna.py", "source_location": "L139"}, {"caller_nid": "tests_test_fauna_testfaunaschema_test_lepidoptera_supported_empty_input", "callee": "assertEqual", "is_member_call": true, "source_file": "C:\\Users\\Marci\\Documents\\GitHub\\PermaDesign\\tests\\test_fauna.py", "source_location": "L142"}, {"caller_nid": "tests_test_fauna_testfaunaschema_test_lepidoptera_supported_empty_input", "callee": "lepidoptera_supported_by_plants", "is_member_call": false, "source_file": "C:\\Users\\Marci\\Documents\\GitHub\\PermaDesign\\tests\\test_fauna.py", "source_location": "L142"}, {"caller_nid": "tests_test_fauna_testfaunaschema_test_lepidoptera_supported_empty_input", "callee": "set", "is_member_call": false, "source_file": "C:\\Users\\Marci\\Documents\\GitHub\\PermaDesign\\tests\\test_fauna.py", "source_location": "L142"}, {"caller_nid": "tests_test_fauna_testfaunaschema_test_lepidoptera_supported_union_grows_with_more_plants", "callee": "lepidoptera_supported_by_plants", "is_member_call": false, "source_file": "C:\\Users\\Marci\\Documents\\GitHub\\PermaDesign\\tests\\test_fauna.py", "source_location": "L148"}, {"caller_nid": "tests_test_fauna_testfaunaschema_test_lepidoptera_supported_union_grows_with_more_plants", "callee": "lepidoptera_supported_by_plants", "is_member_call": false, "source_file": "C:\\Users\\Marci\\Documents\\GitHub\\PermaDesign\\tests\\test_fauna.py", "source_location": "L149"}, {"caller_nid": "tests_test_fauna_testfaunaschema_test_lepidoptera_supported_union_grows_with_more_plants", "callee": "lepidoptera_supported_by_plants", "is_member_call": false, "source_file": "C:\\Users\\Marci\\Documents\\GitHub\\PermaDesign\\tests\\test_fauna.py", "source_location": "L150"}, {"caller_nid": "tests_test_fauna_testfaunaschema_test_lepidoptera_supported_union_grows_with_more_plants", "callee": "assertGreaterEqual", "is_member_call": true, "source_file": "C:\\Users\\Marci\\Documents\\GitHub\\PermaDesign\\tests\\test_fauna.py", "source_location": "L152"}, {"caller_nid": "tests_test_fauna_testfaunaschema_test_lepidoptera_supported_union_grows_with_more_plants", "callee": "len", "is_member_call": false, "source_file": "C:\\Users\\Marci\\Documents\\GitHub\\PermaDesign\\tests\\test_fauna.py", "source_location": "L152"}, {"caller_nid": "tests_test_fauna_testfaunaschema_test_lepidoptera_supported_union_grows_with_more_plants", "callee": "len", "is_member_call": false, "source_file": "C:\\Users\\Marci\\Documents\\GitHub\\PermaDesign\\tests\\test_fauna.py", "source_location": "L152"}, {"caller_nid": "tests_test_fauna_testfaunaschema_test_lepidoptera_supported_union_grows_with_more_plants", "callee": "assertGreaterEqual", "is_member_call": true, "source_file": "C:\\Users\\Marci\\Documents\\GitHub\\PermaDesign\\tests\\test_fauna.py", "source_location": "L153"}, {"caller_nid": "tests_test_fauna_testfaunaschema_test_lepidoptera_supported_union_grows_with_more_plants", "callee": "len", "is_member_call": false, "source_file": "C:\\Users\\Marci\\Documents\\GitHub\\PermaDesign\\tests\\test_fauna.py", "source_location": "L153"}, {"caller_nid": "tests_test_fauna_testfaunaschema_test_lepidoptera_supported_union_grows_with_more_plants", "callee": "len", "is_member_call": false, "source_file": "C:\\Users\\Marci\\Documents\\GitHub\\PermaDesign\\tests\\test_fauna.py", "source_location": "L153"}, {"caller_nid": "tests_test_fauna_testfaunaschema_test_lepidoptera_supported_union_grows_with_more_plants", "callee": "assertIn", "is_member_call": true, "source_file": "C:\\Users\\Marci\\Documents\\GitHub\\PermaDesign\\tests\\test_fauna.py", "source_location": "L155"}, {"caller_nid": "tests_test_fauna_testfaunaschema_test_fauna_supported_per_taxon", "callee": "fauna_supported_by_plants", "is_member_call": false, "source_file": "C:\\Users\\Marci\\Documents\\GitHub\\PermaDesign\\tests\\test_fauna.py", "source_location": "L159"}, {"caller_nid": "tests_test_fauna_testfaunaschema_test_fauna_supported_per_taxon", "callee": "fauna_supported_by_plants", "is_member_call": false, "source_file": "C:\\Users\\Marci\\Documents\\GitHub\\PermaDesign\\tests\\test_fauna.py", "source_location": "L160"}, {"caller_nid": "tests_test_fauna_testfaunaschema_test_fauna_supported_per_taxon", "callee": "assertGreater", "is_member_call": true, "source_file": "C:\\Users\\Marci\\Documents\\GitHub\\PermaDesign\\tests\\test_fauna.py", "source_location": "L164"}, {"caller_nid": "tests_test_fauna_testfaunaschema_test_fauna_supported_per_taxon", "callee": "len", "is_member_call": false, "source_file": "C:\\Users\\Marci\\Documents\\GitHub\\PermaDesign\\tests\\test_fauna.py", "source_location": "L164"}, {"caller_nid": "tests_test_fauna_testfaunaschema_test_fauna_supported_per_taxon", "callee": "assertGreater", "is_member_call": true, "source_file": "C:\\Users\\Marci\\Documents\\GitHub\\PermaDesign\\tests\\test_fauna.py", "source_location": "L165"}, {"caller_nid": "tests_test_fauna_testfaunaschema_test_fauna_supported_per_taxon", "callee": "len", "is_member_call": false, "source_file": "C:\\Users\\Marci\\Documents\\GitHub\\PermaDesign\\tests\\test_fauna.py", "source_location": "L165"}]}