{"nodes": [{"id": "c_users_marci_documents_github_permadesign_src_solar_py", "label": "solar.py", "file_type": "code", "source_file": "C:\\Users\\Marci\\Documents\\GitHub\\PermaDesign\\src\\solar.py", "source_location": "L1"}, {"id": "src_solar_sunposition", "label": "SunPosition", "file_type": "code", "source_file": "C:\\Users\\Marci\\Documents\\GitHub\\PermaDesign\\src\\solar.py", "source_location": "L18"}, {"id": "namedtuple", "label": "NamedTuple", "file_type": "code", "source_file": "", "source_location": ""}, {"id": "src_solar_sun_position", "label": "sun_position()", "file_type": "code", "source_file": "C:\\Users\\Marci\\Documents\\GitHub\\PermaDesign\\src\\solar.py", "source_location": "L25"}, {"id": "float", "label": "float", "file_type": "code", "source_file": "C:\\Users\\Marci\\Documents\\GitHub\\PermaDesign\\src\\solar.py", "source_location": "L25"}, {"id": "datetime", "label": "datetime", "file_type": "code", "source_file": "C:\\Users\\Marci\\Documents\\GitHub\\PermaDesign\\src\\solar.py", "source_location": "L25"}, {"id": "src_solar_sun_path_for_date", "label": "sun_path_for_date()", "file_type": "code", "source_file": "C:\\Users\\Marci\\Documents\\GitHub\\PermaDesign\\src\\solar.py", "source_location": "L81"}, {"id": "date", "label": "date", "file_type": "code", "source_file": "C:\\Users\\Marci\\Documents\\GitHub\\PermaDesign\\src\\solar.py", "source_location": "L81"}, {"id": "int", "label": "int", "file_type": "code", "source_file": "C:\\Users\\Marci\\Documents\\GitHub\\PermaDesign\\src\\solar.py", "source_location": "L81"}, {"id": "src_solar_sunrise_sunset", "label": "sunrise_sunset()", "file_type": "code", "source_file": "C:\\Users\\Marci\\Documents\\GitHub\\PermaDesign\\src\\solar.py", "source_location": "L100"}, {"id": "src_solar_shadow_azimuth", "label": "shadow_azimuth()", "file_type": "code", "source_file": "C:\\Users\\Marci\\Documents\\GitHub\\PermaDesign\\src\\solar.py", "source_location": "L121"}, {"id": "src_solar_shadow_length_factor", "label": "shadow_length_factor()", "file_type": "code", "source_file": "C:\\Users\\Marci\\Documents\\GitHub\\PermaDesign\\src\\solar.py", "source_location": "L126"}, {"id": "src_solar_rationale_1", "label": "solar.py \u2014 Solar position calculations for sun path overlay.  Uses simplified", "file_type": "rationale", "source_file": "C:\\Users\\Marci\\Documents\\GitHub\\PermaDesign\\src\\solar.py", "source_location": "L1"}, {"id": "src_solar_rationale_19", "label": "Sun position at a given moment.", "file_type": "rationale", "source_file": "C:\\Users\\Marci\\Documents\\GitHub\\PermaDesign\\src\\solar.py", "source_location": "L19"}, {"id": "src_solar_rationale_26", "label": "Compute sun altitude and azimuth for a given location and UTC datetime.      P", "file_type": "rationale", "source_file": "C:\\Users\\Marci\\Documents\\GitHub\\PermaDesign\\src\\solar.py", "source_location": "L26"}, {"id": "src_solar_rationale_83", "label": "Compute sun positions throughout a day at evenly-spaced intervals.     Returns", "file_type": "rationale", "source_file": "C:\\Users\\Marci\\Documents\\GitHub\\PermaDesign\\src\\solar.py", "source_location": "L83"}, {"id": "src_solar_rationale_101", "label": "Approximate sunrise and sunset times as decimal hours (local solar time).     R", "file_type": "rationale", "source_file": "C:\\Users\\Marci\\Documents\\GitHub\\PermaDesign\\src\\solar.py", "source_location": "L101"}, {"id": "src_solar_rationale_122", "label": "Shadow direction is opposite the sun azimuth.", "file_type": "rationale", "source_file": "C:\\Users\\Marci\\Documents\\GitHub\\PermaDesign\\src\\solar.py", "source_location": "L122"}, {"id": "src_solar_rationale_127", "label": "Ratio of shadow length to object height.     shadow_length = object_height * sh", "file_type": "rationale", "source_file": "C:\\Users\\Marci\\Documents\\GitHub\\PermaDesign\\src\\solar.py", "source_location": "L127"}], "edges": [{"source": "c_users_marci_documents_github_permadesign_src_solar_py", "target": "math", "relation": "imports", "context": "import", "confidence": "EXTRACTED", "source_file": "C:\\Users\\Marci\\Documents\\GitHub\\PermaDesign\\src\\solar.py", "source_location": "L13", "weight": 1.0}, {"source": "c_users_marci_documents_github_permadesign_src_solar_py", "target": "datetime", "relation": "imports_from", "context": "import", "confidence": "EXTRACTED", "source_file": "C:\\Users\\Marci\\Documents\\GitHub\\PermaDesign\\src\\solar.py", "source_location": "L14", "weight": 1.0}, {"source": "c_users_marci_documents_github_permadesign_src_solar_py", "target": "typing", "relation": "imports_from", "context": "import", "confidence": "EXTRACTED", "source_file": "C:\\Users\\Marci\\Documents\\GitHub\\PermaDesign\\src\\solar.py", "source_location": "L15", "weight": 1.0}, {"source": "c_users_marci_documents_github_permadesign_src_solar_py", "target": "src_solar_sunposition", "relation": "contains", "confidence": "EXTRACTED", "source_file": "C:\\Users\\Marci\\Documents\\GitHub\\PermaDesign\\src\\solar.py", "source_location": "L18", "weight": 1.0}, {"source": "src_solar_sunposition", "target": "namedtuple", "relation": "inherits", "confidence": "EXTRACTED", "source_file": "C:\\Users\\Marci\\Documents\\GitHub\\PermaDesign\\src\\solar.py", "source_location": "L18", "weight": 1.0}, {"source": "c_users_marci_documents_github_permadesign_src_solar_py", "target": "src_solar_sun_position", "relation": "contains", "confidence": "EXTRACTED", "source_file": "C:\\Users\\Marci\\Documents\\GitHub\\PermaDesign\\src\\solar.py", "source_location": "L25", "weight": 1.0}, {"source": "src_solar_sun_position", "target": "float", "relation": "references", "context": "parameter_type", "confidence": "EXTRACTED", "source_file": "C:\\Users\\Marci\\Documents\\GitHub\\PermaDesign\\src\\solar.py", "source_location": "L25", "weight": 1.0}, {"source": "src_solar_sun_position", "target": "float", "relation": "references", "context": "parameter_type", "confidence": "EXTRACTED", "source_file": "C:\\Users\\Marci\\Documents\\GitHub\\PermaDesign\\src\\solar.py", "source_location": "L25", "weight": 1.0}, {"source": "src_solar_sun_position", "target": "datetime", "relation": "references", "context": "parameter_type", "confidence": "EXTRACTED", "source_file": "C:\\Users\\Marci\\Documents\\GitHub\\PermaDesign\\src\\solar.py", "source_location": "L25", "weight": 1.0}, {"source": "src_solar_sun_position", "target": "src_solar_sunposition", "relation": "references", "context": "return_type", "confidence": "EXTRACTED", "source_file": "C:\\Users\\Marci\\Documents\\GitHub\\PermaDesign\\src\\solar.py", "source_location": "L25", "weight": 1.0}, {"source": "c_users_marci_documents_github_permadesign_src_solar_py", "target": "src_solar_sun_path_for_date", "relation": "contains", "confidence": "EXTRACTED", "source_file": "C:\\Users\\Marci\\Documents\\GitHub\\PermaDesign\\src\\solar.py", "source_location": "L81", "weight": 1.0}, {"source": "src_solar_sun_path_for_date", "target": "float", "relation": "references", "context": "parameter_type", "confidence": "EXTRACTED", "source_file": "C:\\Users\\Marci\\Documents\\GitHub\\PermaDesign\\src\\solar.py", "source_location": "L81", "weight": 1.0}, {"source": "src_solar_sun_path_for_date", "target": "float", "relation": "references", "context": "parameter_type", "confidence": "EXTRACTED", "source_file": "C:\\Users\\Marci\\Documents\\GitHub\\PermaDesign\\src\\solar.py", "source_location": "L81", "weight": 1.0}, {"source": "src_solar_sun_path_for_date", "target": "date", "relation": "references", "context": "parameter_type", "confidence": "EXTRACTED", "source_file": "C:\\Users\\Marci\\Documents\\GitHub\\PermaDesign\\src\\solar.py", "source_location": "L81", "weight": 1.0}, {"source": "src_solar_sun_path_for_date", "target": "int", "relation": "references", "context": "parameter_type", "confidence": "EXTRACTED", "source_file": "C:\\Users\\Marci\\Documents\\GitHub\\PermaDesign\\src\\solar.py", "source_location": "L81", "weight": 1.0}, {"source": "src_solar_sun_path_for_date", "target": "src_solar_sunposition", "relation": "references", "context": "generic_arg", "confidence": "EXTRACTED", "source_file": "C:\\Users\\Marci\\Documents\\GitHub\\PermaDesign\\src\\solar.py", "source_location": "L81", "weight": 1.0}, {"source": "c_users_marci_documents_github_permadesign_src_solar_py", "target": "src_solar_sunrise_sunset", "relation": "contains", "confidence": "EXTRACTED", "source_file": "C:\\Users\\Marci\\Documents\\GitHub\\PermaDesign\\src\\solar.py", "source_location": "L100", "weight": 1.0}, {"source": "src_solar_sunrise_sunset", "target": "float", "relation": "references", "context": "parameter_type", "confidence": "EXTRACTED", "source_file": "C:\\Users\\Marci\\Documents\\GitHub\\PermaDesign\\src\\solar.py", "source_location": "L100", "weight": 1.0}, {"source": "src_solar_sunrise_sunset", "target": "float", "relation": "references", "context": "parameter_type", "confidence": "EXTRACTED", "source_file": "C:\\Users\\Marci\\Documents\\GitHub\\PermaDesign\\src\\solar.py", "source_location": "L100", "weight": 1.0}, {"source": "src_solar_sunrise_sunset", "target": "date", "relation": "references", "context": "parameter_type", "confidence": "EXTRACTED", "source_file": "C:\\Users\\Marci\\Documents\\GitHub\\PermaDesign\\src\\solar.py", "source_location": "L100", "weight": 1.0}, {"source": "src_solar_sunrise_sunset", "target": "float", "relation": "references", "context": "generic_arg", "confidence": "EXTRACTED", "source_file": "C:\\Users\\Marci\\Documents\\GitHub\\PermaDesign\\src\\solar.py", "source_location": "L100", "weight": 1.0}, {"source": "src_solar_sunrise_sunset", "target": "float", "relation": "references", "context": "generic_arg", "confidence": "EXTRACTED", "source_file": "C:\\Users\\Marci\\Documents\\GitHub\\PermaDesign\\src\\solar.py", "source_location": "L100", "weight": 1.0}, {"source": "c_users_marci_documents_github_permadesign_src_solar_py", "target": "src_solar_shadow_azimuth", "relation": "contains", "confidence": "EXTRACTED", "source_file": "C:\\Users\\Marci\\Documents\\GitHub\\PermaDesign\\src\\solar.py", "source_location": "L121", "weight": 1.0}, {"source": "src_solar_shadow_azimuth", "target": "float", "relation": "references", "context": "parameter_type", "confidence": "EXTRACTED", "source_file": "C:\\Users\\Marci\\Documents\\GitHub\\PermaDesign\\src\\solar.py", "source_location": "L121", "weight": 1.0}, {"source": "src_solar_shadow_azimuth", "target": "float", "relation": "references", "context": "return_type", "confidence": "EXTRACTED", "source_file": "C:\\Users\\Marci\\Documents\\GitHub\\PermaDesign\\src\\solar.py", "source_location": "L121", "weight": 1.0}, {"source": "c_users_marci_documents_github_permadesign_src_solar_py", "target": "src_solar_shadow_length_factor", "relation": "contains", "confidence": "EXTRACTED", "source_file": "C:\\Users\\Marci\\Documents\\GitHub\\PermaDesign\\src\\solar.py", "source_location": "L126", "weight": 1.0}, {"source": "src_solar_shadow_length_factor", "target": "float", "relation": "references", "context": "parameter_type", "confidence": "EXTRACTED", "source_file": "C:\\Users\\Marci\\Documents\\GitHub\\PermaDesign\\src\\solar.py", "source_location": "L126", "weight": 1.0}, {"source": "src_solar_shadow_length_factor", "target": "float", "relation": "references", "context": "return_type", "confidence": "EXTRACTED", "source_file": "C:\\Users\\Marci\\Documents\\GitHub\\PermaDesign\\src\\solar.py", "source_location": "L126", "weight": 1.0}, {"source": "src_solar_sun_position", "target": "src_solar_sunposition", "relation": "calls", "context": "call", "confidence": "EXTRACTED", "source_file": "C:\\Users\\Marci\\Documents\\GitHub\\PermaDesign\\src\\solar.py", "source_location": "L78", "weight": 1.0}, {"source": "src_solar_sun_path_for_date", "target": "int", "relation": "calls", "context": "call", "confidence": "EXTRACTED", "source_file": "C:\\Users\\Marci\\Documents\\GitHub\\PermaDesign\\src\\solar.py", "source_location": "L91", "weight": 1.0}, {"source": "src_solar_sun_path_for_date", "target": "datetime", "relation": "calls", "context": "call", "confidence": "EXTRACTED", "source_file": "C:\\Users\\Marci\\Documents\\GitHub\\PermaDesign\\src\\solar.py", "source_location": "L93", "weight": 1.0}, {"source": "src_solar_sun_path_for_date", "target": "src_solar_sun_position", "relation": "calls", "context": "call", "confidence": "EXTRACTED", "source_file": "C:\\Users\\Marci\\Documents\\GitHub\\PermaDesign\\src\\solar.py", "source_location": "L94", "weight": 1.0}, {"source": "src_solar_shadow_length_factor", "target": "float", "relation": "calls", "context": "call", "confidence": "EXTRACTED", "source_file": "C:\\Users\\Marci\\Documents\\GitHub\\PermaDesign\\src\\solar.py", "source_location": "L132", "weight": 1.0}, {"source": "src_solar_rationale_1", "target": "c_users_marci_documents_github_permadesign_src_solar_py", "relation": "rationale_for", "confidence": "EXTRACTED", "source_file": "C:\\Users\\Marci\\Documents\\GitHub\\PermaDesign\\src\\solar.py", "source_location": "L1", "weight": 1.0}, {"source": "src_solar_rationale_19", "target": "src_solar_sunposition", "relation": "rationale_for", "confidence": "EXTRACTED", "source_file": "C:\\Users\\Marci\\Documents\\GitHub\\PermaDesign\\src\\solar.py", "source_location": "L19", "weight": 1.0}, {"source": "src_solar_rationale_26", "target": "src_solar_sun_position", "relation": "rationale_for", "confidence": "EXTRACTED", "source_file": "C:\\Users\\Marci\\Documents\\GitHub\\PermaDesign\\src\\solar.py", "source_location": "L26", "weight": 1.0}, {"source": "src_solar_rationale_83", "target": "src_solar_sun_path_for_date", "relation": "rationale_for", "confidence": "EXTRACTED", "source_file": "C:\\Users\\Marci\\Documents\\GitHub\\PermaDesign\\src\\solar.py", "source_location": "L83", "weight": 1.0}, {"source": "src_solar_rationale_101", "target": "src_solar_sunrise_sunset", "relation": "rationale_for", "confidence": "EXTRACTED", "source_file": "C:\\Users\\Marci\\Documents\\GitHub\\PermaDesign\\src\\solar.py", "source_location": "L101", "weight": 1.0}, {"source": "src_solar_rationale_122", "target": "src_solar_shadow_azimuth", "relation": "rationale_for", "confidence": "EXTRACTED", "source_file": "C:\\Users\\Marci\\Documents\\GitHub\\PermaDesign\\src\\solar.py", "source_location": "L122", "weight": 1.0}, {"source": "src_solar_rationale_127", "target": "src_solar_shadow_length_factor", "relation": "rationale_for", "confidence": "EXTRACTED", "source_file": "C:\\Users\\Marci\\Documents\\GitHub\\PermaDesign\\src\\solar.py", "source_location": "L127", "weight": 1.0}], "raw_calls": [{"caller_nid": "src_solar_sun_position", "callee": "timetuple", "is_member_call": true, "source_file": "C:\\Users\\Marci\\Documents\\GitHub\\PermaDesign\\src\\solar.py", "source_location": "L41"}, {"caller_nid": "src_solar_sun_position", "callee": "radians", "is_member_call": true, "source_file": "C:\\Users\\Marci\\Documents\\GitHub\\PermaDesign\\src\\solar.py", "source_location": "L44"}, {"caller_nid": "src_solar_sun_position", "callee": "radians", "is_member_call": true, "source_file": "C:\\Users\\Marci\\Documents\\GitHub\\PermaDesign\\src\\solar.py", "source_location": "L45"}, {"caller_nid": "src_solar_sun_position", "callee": "sin", "is_member_call": true, "source_file": "C:\\Users\\Marci\\Documents\\GitHub\\PermaDesign\\src\\solar.py", "source_location": "L46"}, {"caller_nid": "src_solar_sun_position", "callee": "sin", "is_member_call": true, "source_file": "C:\\Users\\Marci\\Documents\\GitHub\\PermaDesign\\src\\solar.py", "source_location": "L50"}, {"caller_nid": "src_solar_sun_position", "callee": "cos", "is_member_call": true, "source_file": "C:\\Users\\Marci\\Documents\\GitHub\\PermaDesign\\src\\solar.py", "source_location": "L50"}, {"caller_nid": "src_solar_sun_position", "callee": "sin", "is_member_call": true, "source_file": "C:\\Users\\Marci\\Documents\\GitHub\\PermaDesign\\src\\solar.py", "source_location": "L50"}, {"caller_nid": "src_solar_sun_position", "callee": "radians", "is_member_call": true, "source_file": "C:\\Users\\Marci\\Documents\\GitHub\\PermaDesign\\src\\solar.py", "source_location": "L59"}, {"caller_nid": "src_solar_sun_position", "callee": "radians", "is_member_call": true, "source_file": "C:\\Users\\Marci\\Documents\\GitHub\\PermaDesign\\src\\solar.py", "source_location": "L61"}, {"caller_nid": "src_solar_sun_position", "callee": "sin", "is_member_call": true, "source_file": "C:\\Users\\Marci\\Documents\\GitHub\\PermaDesign\\src\\solar.py", "source_location": "L64"}, {"caller_nid": "src_solar_sun_position", "callee": "sin", "is_member_call": true, "source_file": "C:\\Users\\Marci\\Documents\\GitHub\\PermaDesign\\src\\solar.py", "source_location": "L64"}, {"caller_nid": "src_solar_sun_position", "callee": "cos", "is_member_call": true, "source_file": "C:\\Users\\Marci\\Documents\\GitHub\\PermaDesign\\src\\solar.py", "source_location": "L65"}, {"caller_nid": "src_solar_sun_position", "callee": "cos", "is_member_call": true, "source_file": "C:\\Users\\Marci\\Documents\\GitHub\\PermaDesign\\src\\solar.py", "source_location": "L65"}, {"caller_nid": "src_solar_sun_position", "callee": "cos", "is_member_call": true, "source_file": "C:\\Users\\Marci\\Documents\\GitHub\\PermaDesign\\src\\solar.py", "source_location": "L65"}, {"caller_nid": "src_solar_sun_position", "callee": "max", "is_member_call": false, "source_file": "C:\\Users\\Marci\\Documents\\GitHub\\PermaDesign\\src\\solar.py", "source_location": "L66"}, {"caller_nid": "src_solar_sun_position", "callee": "min", "is_member_call": false, "source_file": "C:\\Users\\Marci\\Documents\\GitHub\\PermaDesign\\src\\solar.py", "source_location": "L66"}, {"caller_nid": "src_solar_sun_position", "callee": "degrees", "is_member_call": true, "source_file": "C:\\Users\\Marci\\Documents\\GitHub\\PermaDesign\\src\\solar.py", "source_location": "L67"}, {"caller_nid": "src_solar_sun_position", "callee": "asin", "is_member_call": true, "source_file": "C:\\Users\\Marci\\Documents\\GitHub\\PermaDesign\\src\\solar.py", "source_location": "L67"}, {"caller_nid": "src_solar_sun_position", "callee": "sin", "is_member_call": true, "source_file": "C:\\Users\\Marci\\Documents\\GitHub\\PermaDesign\\src\\solar.py", "source_location": "L70"}, {"caller_nid": "src_solar_sun_position", "callee": "sin", "is_member_call": true, "source_file": "C:\\Users\\Marci\\Documents\\GitHub\\PermaDesign\\src\\solar.py", "source_location": "L70"}, {"caller_nid": "src_solar_sun_position", "callee": "cos", "is_member_call": true, "source_file": "C:\\Users\\Marci\\Documents\\GitHub\\PermaDesign\\src\\solar.py", "source_location": "L71"}, {"caller_nid": "src_solar_sun_position", "callee": "cos", "is_member_call": true, "source_file": "C:\\Users\\Marci\\Documents\\GitHub\\PermaDesign\\src\\solar.py", "source_location": "L71"}, {"caller_nid": "src_solar_sun_position", "callee": "radians", "is_member_call": true, "source_file": "C:\\Users\\Marci\\Documents\\GitHub\\PermaDesign\\src\\solar.py", "source_location": "L71"}, {"caller_nid": "src_solar_sun_position", "callee": "max", "is_member_call": false, "source_file": "C:\\Users\\Marci\\Documents\\GitHub\\PermaDesign\\src\\solar.py", "source_location": "L72"}, {"caller_nid": "src_solar_sun_position", "callee": "min", "is_member_call": false, "source_file": "C:\\Users\\Marci\\Documents\\GitHub\\PermaDesign\\src\\solar.py", "source_location": "L72"}, {"caller_nid": "src_solar_sun_position", "callee": "degrees", "is_member_call": true, "source_file": "C:\\Users\\Marci\\Documents\\GitHub\\PermaDesign\\src\\solar.py", "source_location": "L73"}, {"caller_nid": "src_solar_sun_position", "callee": "acos", "is_member_call": true, "source_file": "C:\\Users\\Marci\\Documents\\GitHub\\PermaDesign\\src\\solar.py", "source_location": "L73"}, {"caller_nid": "src_solar_sun_path_for_date", "callee": "range", "is_member_call": false, "source_file": "C:\\Users\\Marci\\Documents\\GitHub\\PermaDesign\\src\\solar.py", "source_location": "L88"}, {"caller_nid": "src_solar_sun_path_for_date", "callee": "append", "is_member_call": true, "source_file": "C:\\Users\\Marci\\Documents\\GitHub\\PermaDesign\\src\\solar.py", "source_location": "L96"}, {"caller_nid": "src_solar_sunrise_sunset", "callee": "timetuple", "is_member_call": true, "source_file": "C:\\Users\\Marci\\Documents\\GitHub\\PermaDesign\\src\\solar.py", "source_location": "L105"}, {"caller_nid": "src_solar_sunrise_sunset", "callee": "radians", "is_member_call": true, "source_file": "C:\\Users\\Marci\\Documents\\GitHub\\PermaDesign\\src\\solar.py", "source_location": "L106"}, {"caller_nid": "src_solar_sunrise_sunset", "callee": "sin", "is_member_call": true, "source_file": "C:\\Users\\Marci\\Documents\\GitHub\\PermaDesign\\src\\solar.py", "source_location": "L107"}, {"caller_nid": "src_solar_sunrise_sunset", "callee": "radians", "is_member_call": true, "source_file": "C:\\Users\\Marci\\Documents\\GitHub\\PermaDesign\\src\\solar.py", "source_location": "L109"}, {"caller_nid": "src_solar_sunrise_sunset", "callee": "radians", "is_member_call": true, "source_file": "C:\\Users\\Marci\\Documents\\GitHub\\PermaDesign\\src\\solar.py", "source_location": "L110"}, {"caller_nid": "src_solar_sunrise_sunset", "callee": "tan", "is_member_call": true, "source_file": "C:\\Users\\Marci\\Documents\\GitHub\\PermaDesign\\src\\solar.py", "source_location": "L112"}, {"caller_nid": "src_solar_sunrise_sunset", "callee": "tan", "is_member_call": true, "source_file": "C:\\Users\\Marci\\Documents\\GitHub\\PermaDesign\\src\\solar.py", "source_location": "L112"}, {"caller_nid": "src_solar_sunrise_sunset", "callee": "max", "is_member_call": false, "source_file": "C:\\Users\\Marci\\Documents\\GitHub\\PermaDesign\\src\\solar.py", "source_location": "L113"}, {"caller_nid": "src_solar_sunrise_sunset", "callee": "min", "is_member_call": false, "source_file": "C:\\Users\\Marci\\Documents\\GitHub\\PermaDesign\\src\\solar.py", "source_location": "L113"}, {"caller_nid": "src_solar_sunrise_sunset", "callee": "degrees", "is_member_call": true, "source_file": "C:\\Users\\Marci\\Documents\\GitHub\\PermaDesign\\src\\solar.py", "source_location": "L114"}, {"caller_nid": "src_solar_sunrise_sunset", "callee": "acos", "is_member_call": true, "source_file": "C:\\Users\\Marci\\Documents\\GitHub\\PermaDesign\\src\\solar.py", "source_location": "L114"}, {"caller_nid": "src_solar_shadow_length_factor", "callee": "tan", "is_member_call": true, "source_file": "C:\\Users\\Marci\\Documents\\GitHub\\PermaDesign\\src\\solar.py", "source_location": "L133"}, {"caller_nid": "src_solar_shadow_length_factor", "callee": "radians", "is_member_call": true, "source_file": "C:\\Users\\Marci\\Documents\\GitHub\\PermaDesign\\src\\solar.py", "source_location": "L133"}]}